{"bseNseJson":[{"etSymbol":"gacl","dateTime":"10:47 | 26-05-2021","listingFlag":true,"bestSellPrice":"321.85","symbol":"AMBUJACEM","preMarket":false,"trend":"equal","companyName":"Ambuja Cements","sectorRank":"3","openPrice":"322.45","industry":"Cement - Pan India","instrument":"Equity","bestBuyQty":"240","companyName2":"Ambuja Cements Ltd.","seoName":"ambuja-cements-ltd","companyRankYear":"2020","fiftyTwoWeekHighDateTime":"Apr  9 2021  4:00PM","fiftyTwoWeekHighPrice":"329.90","lowPrice":"319.35","segment":"BSE","highPrice":"322.95","scripCode":"500425","exchangeGroup":"A","sector":"Cement","lastTradedPrice":"321.70","value":"1.04","netChange":"-0.75","percentChange":"-0.23","displayDateTime":"2021-05-26 10:47:00","companyType":"equity","tpilCode":"1506","bestSellQty":"288","volume":"32615","companyId":"13643","groupName":"A ","fiftyTwoWeekLowDateTime":"Jun 12 2020  4:00PM","faceValue":"2.00","companyRank":"65","fiftyTwoWeekLowPrice":"181.75","nseScripCode":"AMBUJACEM","closePrice":"322.45","isSME":false,"bestBuyPrice":"321.60","isinCode":"INE079A01024"},{"etSymbol":"ambcel","dateTime":"10:47 | 26-05-2021","listingFlag":true,"bestSellPrice":"321.75","symbol":"AMBUJACEM","preMarket":false,"trend":"equal","companyName":"Ambuja Cements","sectorRank":"3","openPrice":"322.30","industry":"Cement - Pan India","instrument":"Equity","bestBuyQty":"3365","companyName2":"Ambuja Cements Ltd.","seoName":"ambuja-cements-ltd","companyRankYear":"2020","fiftyTwoWeekHighDateTime":"Apr  9 2021  3:59PM","fiftyTwoWeekHighPrice":"329.90","lowPrice":"319.40","segment":"NSE","highPrice":"322.85","scripCode":"500425","exchangeGroup":"Jr.Nifty","sector":"Cement","lastTradedPrice":"321.75","value":"20.24","netChange":"-0.55","percentChange":"-0.17","displayDateTime":"2021-05-26 10:47:00","companyType":"equity","tpilCode":"1506","bestSellQty":"1329","volume":"629790","companyId":"13643","fiftyTwoWeekLowDateTime":"Jun 12 2020  3:59PM","faceValue":"2.00","wightedAverage":"321.34","companyRank":"65","fiftyTwoWeekLowPrice":"181.65","nseScripCode":"AMBUJACEMEQ","closePrice":"322.30","isSME":false,"bestBuyPrice":"321.65","isinCode":"INE079A01024"}],"companySD":[{"companyType":"equity","securitySubTypeId":"4","companyName":"Ambuja Cements Ltd.","exchangeId":"50","year3sd":"1.9879","companyId":"13643","year1sd":"2.4638","securityTypeId":"5","month1sd":"1.7553","modified":"2020-06-23 10:59:12.0","id":"10626","month6sd":"2.7831","month3sd":"2.6519"},{"companyType":"equity","securitySubTypeId":"4","companyName":"Ambuja Cements Ltd.","exchangeId":"47","year3sd":"1.9757","companyId":"13643","year1sd":"2.4754","securityTypeId":"5","month1sd":"1.7013","modified":"2020-06-23 10:59:12.0","id":"10625","month6sd":"2.8389","month3sd":"2.7401"}],"averageVolume":{"NSE":{"exchangeId":"50","companyid":"13643","fiveDaysAverage":"5784296.6000","tenDaysAverage":"4978043.0000","oneMonthAverage":"6483600.6333"},"BSE":{"exchangeId":"47","companyid":"13643","fiveDaysAverage":"231492.6000","tenDaysAverage":"202910.1000","oneMonthAverage":"283457.8000"}},"companyBeta":[{"exchangeId":"47","companyId":"13643","oneYearBeta":"1.4398","companyType":"equity","sixMonthBeta":"1.3734","companyName":"Ambuja Cements Ltd.","threeMonthBeta":"1.6840","dateModified":"2019-08-20 01:11:04.0","threeYearBeta":"1.3085","oneMonthBeta":"1.3679"},{"exchangeId":"50","companyId":"13643","oneYearBeta":"1.4341","companyType":"equity","sixMonthBeta":"1.3885","companyName":"Ambuja Cements Ltd.","threeMonthBeta":"1.7237","dateModified":"2019-08-20 01:11:05.0","threeYearBeta":"1.3160","oneMonthBeta":"1.4634"}]}
