{"bseNseJson":[{"dateTime":"10:47 | 26-05-2021","etSymbol":"tcs","bestSellPrice":"3135.00","listingFlag":true,"symbol":"TCS","preMarket":false,"trend":"equal","companyName":"Tata Consultancy","openPrice":"3123.00","sectorRank":"1","industry":"IT Consulting & Software - Large Cap","instrument":"Equity","bestBuyQty":"51","companyName2":"Tata Consultancy Services Ltd.","seoName":"tata-consultancy-services-ltd","fiftyTwoWeekHighDateTime":"Apr  9 2021  4:00PM","companyRankYear":"2020","fiftyTwoWeekHighPrice":"3358.80","lowPrice":"3104.75","segment":"BSE","highPrice":"3138.00","scripCode":"532540","exchangeGroup":"A","sector":"IT Software","lastTradedPrice":"3134.90","value":"5.47","netChange":"20.95","percentChange":"0.67","displayDateTime":"2021-05-26 10:47:00","companyType":"equity","tpilCode":"4300","bestSellQty":"5","volume":"17517","companyId":"8345","groupName":"A ","fiftyTwoWeekLowDateTime":"May 26 2020  4:00PM","faceValue":"1.00","companyRank":"9","fiftyTwoWeekLowPrice":"1925.00","nseScripCode":"TCS","closePrice":"3113.95","isSME":false,"bestBuyPrice":"3134.05","isinCode":"INE467B01029"},{"dateTime":"10:47 | 26-05-2021","etSymbol":"tata6","bestSellPrice":"3135.00","listingFlag":true,"symbol":"TCS","preMarket":false,"trend":"equal","companyName":"Tata Consultancy","openPrice":"3120.00","sectorRank":"1","industry":"IT Consulting & Software - Large Cap","instrument":"Equity","bestBuyQty":"22","companyName2":"Tata Consultancy Services Ltd.","seoName":"tata-consultancy-services-ltd","fiftyTwoWeekHighDateTime":"Apr  9 2021  3:59PM","companyRankYear":"2020","fiftyTwoWeekHighPrice":"3354.35","lowPrice":"3103.80","segment":"NSE","highPrice":"3138.80","scripCode":"532540","exchangeGroup":"Nifty","sector":"IT Software","lastTradedPrice":"3134.50","value":"176.17","netChange":"20.50","percentChange":"0.66","displayDateTime":"2021-05-26 10:47:00","companyType":"equity","tpilCode":"4300","bestSellQty":"131","volume":"563951","companyId":"8345","fiftyTwoWeekLowDateTime":"May 26 2020  3:59PM","faceValue":"1.00","wightedAverage":"3123.85","companyRank":"9","fiftyTwoWeekLowPrice":"1925.00","nseScripCode":"TCSEQ","closePrice":"3114.00","isSME":false,"bestBuyPrice":"3134.55","isinCode":"INE467B01029"}],"companySD":[{"companyType":"equity","securitySubTypeId":"4","companyName":"Tata Consultancy Services Ltd.","exchangeId":"50","year3sd":"1.7198","companyId":"8345","year1sd":"2.1547","securityTypeId":"5","month1sd":"1.7953","modified":"2020-06-23 11:06:39.0","id":"8536","month6sd":"2.6812","month3sd":"2.6524"},{"companyType":"equity","securitySubTypeId":"4","companyName":"Tata Consultancy Services Ltd.","exchangeId":"47","year3sd":"1.7129","companyId":"8345","year1sd":"2.1817","securityTypeId":"5","month1sd":"1.9524","modified":"2020-06-23 11:06:39.0","id":"8535","month6sd":"2.7418","month3sd":"2.7376"}],"averageVolume":{"NSE":{"exchangeId":"50","companyid":"8345","fiveDaysAverage":"1898901.4000","tenDaysAverage":"2092162.5000","oneMonthAverage":"2553451.9333"},"BSE":{"exchangeId":"47","companyid":"8345","fiveDaysAverage":"51521.2000","tenDaysAverage":"61651.5000","oneMonthAverage":"106062.7000"}},"companyBeta":[{"exchangeId":"47","companyId":"8345","oneYearBeta":"0.3960","companyType":"equity","sixMonthBeta":"0.3824","companyName":"Tata Consultancy Services Ltd.","threeMonthBeta":"0.3262","dateModified":"2019-08-20 01:30:28.0","threeYearBeta":"0.3061","oneMonthBeta":"0.0476"},{"exchangeId":"50","companyId":"8345","oneYearBeta":"0.4029","companyType":"equity","sixMonthBeta":"0.4044","companyName":"Tata Consultancy Services Ltd.","threeMonthBeta":"0.3297","dateModified":"2019-08-20 01:30:28.0","threeYearBeta":"0.3110","oneMonthBeta":"0.0364"}]}
